{
  "format": "PhoenixRegressionCaseV1",
  "saved_at": "2026-06-23T21:07:50",
  "game": "01_マツゲン箕島硬式野球部－大阪ガス",
  "memo": "",
  "expected": [
    {
      "inning": "3回裏",
      "score_no": 1,
      "judgment": "非自責点",
      "label": "非自責",
      "reason": "Virtual3アウト",
      "runner": "高橋 佑八"
    },
    {
      "inning": "3回裏",
      "score_no": 2,
      "judgment": "非自責点",
      "label": "非自責",
      "reason": "Virtual3アウト",
      "runner": "橋本 典之"
    },
    {
      "inning": "5回裏",
      "score_no": 1,
      "judgment": "自責点",
      "label": "自責",
      "reason": "自責対象",
      "runner": "島袋 皓平"
    },
    {
      "inning": "5回裏",
      "score_no": 2,
      "judgment": "自責点",
      "label": "自責",
      "reason": "自責対象",
      "runner": "橋本 典之"
    },
    {
      "inning": "6回裏",
      "score_no": 1,
      "judgment": "非自責点",
      "label": "非自責",
      "reason": "Virtual3アウト",
      "runner": "石橋 昂樹"
    },
    {
      "inning": "8回裏",
      "score_no": 1,
      "judgment": "非自責点",
      "label": "非自責",
      "reason": "Virtual3アウト",
      "runner": "山川 晃汰"
    }
  ]
}